numereval/__init__.py
numereval/neutralize.py
numereval/numereval.py
numereval/scores.py
numereval/signalseval.py
numereval-0.2.5.dist-info/LICENSE
numereval-0.2.5.dist-info/METADATA
numereval-0.2.5.dist-info/WHEEL
numereval-0.2.5.dist-info/top_level.txt
numereval-0.2.5.dist-info/RECORD
