Metadata-Version: 2.1
Name: numereval
Version: 0.2.5
Summary: A small package for evaluating numer.ai model locally
Home-page: https://github.com/parmarsuraj99/numereval
Author: Suraj Parmar
Author-email: parmarsuraj99@gmail.com
License: UNKNOWN
Platform: UNKNOWN
Classifier: Programming Language :: Python :: 3
Classifier: License :: OSI Approved :: MIT License
Classifier: Operating System :: OS Independent
Requires-Python: >=3.6
